heatindex.cpython-313-darwin.so
heatindex-0.0.1.dist-info/METADATA
heatindex-0.0.1.dist-info/WHEEL
heatindex-0.0.1.dist-info/licenses/LICENSE
heatindex-0.0.1.dist-info/RECORD
