Metadata-Version: 2.2
Name: heatindex
Version: 0.0.1
Summary: Tools for Calculating Heat Stress
Author-Email: Yi-Chuan Lu <yclu@berkeley.edu>, "David M. Romps" <romps@berkeley.edu>
Maintainer-Email: "David M. Romps" <romps@berkeley.edu>, Yi-Chuan Lu <yclu@berkeley.edu>
License: MIT
Classifier: Development Status :: 4 - Beta
Classifier: License :: OSI Approved :: MIT License
Classifier: Intended Audience :: Science/Research
Classifier: Topic :: Scientific/Engineering
Classifier: Topic :: Scientific/Engineering :: Atmospheric Science
Classifier: Topic :: Scientific/Engineering :: Physics
Classifier: Programming Language :: C++
Classifier: Programming Language :: Python
Classifier: Programming Language :: Python :: 3
Classifier: Programming Language :: Python :: 3 :: Only
Classifier: Programming Language :: Python :: 3.8
Classifier: Programming Language :: Python :: 3.9
Classifier: Programming Language :: Python :: 3.10
Classifier: Programming Language :: Python :: 3.11
Classifier: Programming Language :: Python :: 3.12
Classifier: Programming Language :: Python :: 3.13
Classifier: Operating System :: Microsoft :: Windows
Classifier: Operating System :: Unix
Classifier: Operating System :: MacOS
Project-URL: Homepage, https://heatindex.org
Project-URL: Documentation, https://heatindex.org/docs
Project-URL: Repository, https://github.com/romps/heatindex
Requires-Python: >=3.8
Requires-Dist: numpy
